knot_tube/__init__.py
knot_tube/knot.py
knot_tube/xyz.py
knot_tube-0.1.dist-info/METADATA
knot_tube-0.1.dist-info/WHEEL
knot_tube-0.1.dist-info/top_level.txt
knot_tube-0.1.dist-info/RECORD
